pdfdecrypt/__init__.py
pdfdecrypt/cmd.py
pdfdecrypt/i18n.py
pdfdecrypt/locale/de/LC_MESSAGES/pdfdecrypt.mo
pdfdecrypt/locale/fr/LC_MESSAGES/pdfdecrypt.mo
pdfdecrypt-1.0.dist-info/LICENSE-AGPLv3.txt
pdfdecrypt-1.0.dist-info/METADATA
pdfdecrypt-1.0.dist-info/WHEEL
pdfdecrypt-1.0.dist-info/entry_points.txt
pdfdecrypt-1.0.dist-info/top_level.txt
pdfdecrypt-1.0.dist-info/RECORD
