Metadata-Version: 2.1
Name: pdfdecrypt
Version: 1.0
Summary: Remove passwords from PDF documents
Home-page: https://pdfdecrypt.readthedocs.io/
Author: Hartmut Goebel
Author-email: h.goebel@crazy-compilers.com
License: AGPLv3+
Download-URL: https://pypi.org/project/pdfdecrypt/
Keywords: pdf,decrypt
Platform: UNKNOWN
Classifier: Development Status :: 5 - Production/Stable
Classifier: Environment :: Console
Classifier: Intended Audience :: Developers
Classifier: Intended Audience :: End Users/Desktop
Classifier: Intended Audience :: System Administrators
Classifier: License :: OSI Approved :: GNU Affero General Public License v3 or later (AGPLv3+)
Classifier: Natural Language :: English
Classifier: Natural Language :: German
Classifier: Natural Language :: French
Classifier: Operating System :: OS Independent
Classifier: Programming Language :: Python
Classifier: Programming Language :: Python :: 3
Classifier: Programming Language :: Python :: 3.6
Classifier: Programming Language :: Python :: 3.7
Classifier: Programming Language :: Python :: 3.8
Classifier: Programming Language :: Python :: 3.9
Classifier: Programming Language :: Python :: 3.10
Classifier: Programming Language :: Python :: 3.11
Classifier: Topic :: Utilities
Requires-Dist: PyPDF2[crypto] (<3,>=2.1.1)
